LICENSE.md
MANIFEST.in
README.md
package.json
setup.py
elfinder_client/CNAME
elfinder_client/Changelog
elfinder_client/LICENSE.md
elfinder_client/README.md
elfinder_client/__init__.py
elfinder_client/composer.json
elfinder_client/elFinderSupportBrowserFS.js
elfinder_client/elFinderSupportBrowserFS.js.LICENSE.txt
elfinder_client/elFinderSupportBrowserFS.js.map
elfinder_client/elfinder.html
elfinder_client/elfinder.legacy.html
elfinder_client/index.html
elfinder_client/main.default.js
elfinder_client/package.json
elfinder_client/service-worker.js
elfinder_client/service-worker.js.LICENSE.txt
elfinder_client/service-worker.js.map
elfinder_client.egg-info/PKG-INFO
elfinder_client.egg-info/SOURCES.txt
elfinder_client.egg-info/dependency_links.txt
elfinder_client.egg-info/not-zip-safe
elfinder_client.egg-info/top_level.txt
elfinder_client/css/elfinder.full.css
elfinder_client/css/elfinder.min.css
elfinder_client/css/theme.css
elfinder_client/files/.gitignore
elfinder_client/files/.trash/.gitignore
elfinder_client/img/Screenshot-dialog-elfinder.png
elfinder_client/img/Screenshot-embedded-elfinder.png
elfinder_client/img/arrows-active.png
elfinder_client/img/arrows-normal.png
elfinder_client/img/crop.gif
elfinder_client/img/dialogs.png
elfinder_client/img/editor-icons.png
elfinder_client/img/icons-big.png
elfinder_client/img/icons-big.svg
elfinder_client/img/icons-small.png
elfinder_client/img/imjoy-elfinder-icon.png
elfinder_client/img/imjoy-elfinder-icon.svg
elfinder_client/img/logo.png
elfinder_client/img/progress.gif
elfinder_client/img/quicklook-bg.png
elfinder_client/img/quicklook-icons.png
elfinder_client/img/resize.png
elfinder_client/img/spinner-mini.gif
elfinder_client/img/toolbar.png
elfinder_client/img/trashmesh.png
elfinder_client/img/ui-icons_ffffff_256x240.png
elfinder_client/img/volume_icon_box.png
elfinder_client/img/volume_icon_box.svg
elfinder_client/img/volume_icon_dropbox.png
elfinder_client/img/volume_icon_dropbox.svg
elfinder_client/img/volume_icon_ftp.png
elfinder_client/img/volume_icon_ftp.svg
elfinder_client/img/volume_icon_googledrive.png
elfinder_client/img/volume_icon_googledrive.svg
elfinder_client/img/volume_icon_local.png
