Metadata-Version: 2.1
Name: elfinder-client
Version: 2.1.62a3
Summary: Static files for the elFinder file browser
Home-page: https://github.com/imjoy-team/elFinder/
Author: imjoy-team
Author-email: imjoy.team@gmail.com
License: BSD-3
License-File: LICENSE.md
